youtube_to_kindle/__init__.py
youtube_to_kindle/youtube_to_kindle.py
youtube_to_kindle-1.0.0.dist-info/LICENSE
youtube_to_kindle-1.0.0.dist-info/METADATA
youtube_to_kindle-1.0.0.dist-info/WHEEL
youtube_to_kindle-1.0.0.dist-info/top_level.txt
youtube_to_kindle-1.0.0.dist-info/RECORD
