Metadata-Version: 2.1
Name: youtube-to-kindle
Version: 1.0.0
Summary: A tool to convert YouTube content to Kindle format
Home-page: UNKNOWN
Author: Alexis Kirke
Author-email: alexiskirke2@gmail.com
License: UNKNOWN
Platform: UNKNOWN
Classifier: Programming Language :: Python :: 3
Classifier: License :: OSI Approved :: MIT License
Classifier: Operating System :: OS Independent
Requires-Python: >=3.6
License-File: LICENSE
Requires-Dist: openai
Requires-Dist: tinytag
Requires-Dist: pydub
Requires-Dist: pytube
Requires-Dist: ebooklib
Requires-Dist: tiktoken
